filler/__init__.py
filler/base.py
filler-0.0.1.dist-info/METADATA
filler-0.0.1.dist-info/WHEEL
filler-0.0.1.dist-info/licenses/LICENSE
filler-0.0.1.dist-info/RECORD
