Metadata-Version: 2.3
Name: filler
Version: 0.0.1
Summary: A Python library for batch filling docx templates
Author-email: sencher <sencher@163.com>
License-File: LICENSE
Requires-Dist: docxtpl>=0.18.0
Requires-Dist: pandas>=2.2.3
